helios_web3/__init__.py
helios_web3/abi.py
helios_web3/account.py
helios_web3/admin.py
helios_web3/hls.py
helios_web3/main.py
helios_web3/personal.py
helios_web3/pythonic_middleware.py
helios_web3/temp_fork_files/__init__.py
helios_web3/temp_fork_files/photon.py
helios_web3/utils/__init__.py
helios_web3/utils/block_creation.py
helios_web3/utils/get_version.py
helios_web3/utils/rpc_abi.py
helios_web3-5.0.13.dist-info/LICENSE
helios_web3-5.0.13.dist-info/METADATA
helios_web3-5.0.13.dist-info/WHEEL
helios_web3-5.0.13.dist-info/top_level.txt
helios_web3-5.0.13.dist-info/RECORD
